{"nodes": [{"id": "c_users_novy_desktop_projects_official_yvon_app_api_health_route_ts", "label": "route.ts", "file_type": "code", "source_file": "C:\\Users\\Novy\\Desktop\\Projects\\Official YVON\\app\\api\\health\\route.ts", "source_location": "L1"}, {"id": "route_get", "label": "GET()", "file_type": "code", "source_file": "C:\\Users\\Novy\\Desktop\\Projects\\Official YVON\\app\\api\\health\\route.ts", "source_location": "L12"}], "edges": [{"source": "c_users_novy_desktop_projects_official_yvon_app_api_health_route_ts", "target": "server", "relation": "imports_from", "confidence": "EXTRACTED", "source_file": "C:\\Users\\Novy\\Desktop\\Projects\\Official YVON\\app\\api\\health\\route.ts", "source_location": "L2", "weight": 1.0}, {"source": "c_users_novy_desktop_projects_official_yvon_app_api_health_route_ts", "target": "database", "relation": "imports_from", "confidence": "EXTRACTED", "source_file": "C:\\Users\\Novy\\Desktop\\Projects\\Official YVON\\app\\api\\health\\route.ts", "source_location": "L3", "weight": 1.0}, {"source": "c_users_novy_desktop_projects_official_yvon_app_api_health_route_ts", "target": "website", "relation": "imports_from", "confidence": "EXTRACTED", "source_file": "C:\\Users\\Novy\\Desktop\\Projects\\Official YVON\\app\\api\\health\\route.ts", "source_location": "L4", "weight": 1.0}, {"source": "c_users_novy_desktop_projects_official_yvon_app_api_health_route_ts", "target": "spend", "relation": "imports_from", "confidence": "EXTRACTED", "source_file": "C:\\Users\\Novy\\Desktop\\Projects\\Official YVON\\app\\api\\health\\route.ts", "source_location": "L5", "weight": 1.0}, {"source": "c_users_novy_desktop_projects_official_yvon_app_api_health_route_ts", "target": "repository", "relation": "imports_from", "confidence": "EXTRACTED", "source_file": "C:\\Users\\Novy\\Desktop\\Projects\\Official YVON\\app\\api\\health\\route.ts", "source_location": "L6", "weight": 1.0}, {"source": "c_users_novy_desktop_projects_official_yvon_app_api_health_route_ts", "target": "alerts", "relation": "imports_from", "confidence": "EXTRACTED", "source_file": "C:\\Users\\Novy\\Desktop\\Projects\\Official YVON\\app\\api\\health\\route.ts", "source_location": "L7", "weight": 1.0}, {"source": "c_users_novy_desktop_projects_official_yvon_app_api_health_route_ts", "target": "route_get", "relation": "contains", "confidence": "EXTRACTED", "source_file": "C:\\Users\\Novy\\Desktop\\Projects\\Official YVON\\app\\api\\health\\route.ts", "source_location": "L12", "weight": 1.0}], "raw_calls": [{"caller_nid": "route_get", "callee": "all", "source_file": "C:\\Users\\Novy\\Desktop\\Projects\\Official YVON\\app\\api\\health\\route.ts", "source_location": "L13"}, {"caller_nid": "route_get", "callee": "catch", "source_file": "C:\\Users\\Novy\\Desktop\\Projects\\Official YVON\\app\\api\\health\\route.ts", "source_location": "L14"}, {"caller_nid": "route_get", "callee": "checkDatabaseHealth", "source_file": "C:\\Users\\Novy\\Desktop\\Projects\\Official YVON\\app\\api\\health\\route.ts", "source_location": "L14"}, {"caller_nid": "route_get", "callee": "catch", "source_file": "C:\\Users\\Novy\\Desktop\\Projects\\Official YVON\\app\\api\\health\\route.ts", "source_location": "L15"}, {"caller_nid": "route_get", "callee": "checkWebsiteHealth", "source_file": "C:\\Users\\Novy\\Desktop\\Projects\\Official YVON\\app\\api\\health\\route.ts", "source_location": "L15"}, {"caller_nid": "route_get", "callee": "catch", "source_file": "C:\\Users\\Novy\\Desktop\\Projects\\Official YVON\\app\\api\\health\\route.ts", "source_location": "L16"}, {"caller_nid": "route_get", "callee": "checkSpend", "source_file": "C:\\Users\\Novy\\Desktop\\Projects\\Official YVON\\app\\api\\health\\route.ts", "source_location": "L16"}, {"caller_nid": "route_get", "callee": "catch", "source_file": "C:\\Users\\Novy\\Desktop\\Projects\\Official YVON\\app\\api\\health\\route.ts", "source_location": "L17"}, {"caller_nid": "route_get", "callee": "checkRepositoryHealth", "source_file": "C:\\Users\\Novy\\Desktop\\Projects\\Official YVON\\app\\api\\health\\route.ts", "source_location": "L17"}, {"caller_nid": "route_get", "callee": "every", "source_file": "C:\\Users\\Novy\\Desktop\\Projects\\Official YVON\\app\\api\\health\\route.ts", "source_location": "L20"}, {"caller_nid": "route_get", "callee": "toISOString", "source_file": "C:\\Users\\Novy\\Desktop\\Projects\\Official YVON\\app\\api\\health\\route.ts", "source_location": "L21"}, {"caller_nid": "route_get", "callee": "push", "source_file": "C:\\Users\\Novy\\Desktop\\Projects\\Official YVON\\app\\api\\health\\route.ts", "source_location": "L26"}, {"caller_nid": "route_get", "callee": "push", "source_file": "C:\\Users\\Novy\\Desktop\\Projects\\Official YVON\\app\\api\\health\\route.ts", "source_location": "L27"}, {"caller_nid": "route_get", "callee": "push", "source_file": "C:\\Users\\Novy\\Desktop\\Projects\\Official YVON\\app\\api\\health\\route.ts", "source_location": "L28"}, {"caller_nid": "route_get", "callee": "push", "source_file": "C:\\Users\\Novy\\Desktop\\Projects\\Official YVON\\app\\api\\health\\route.ts", "source_location": "L29"}, {"caller_nid": "route_get", "callee": "writeHealthAlert", "source_file": "C:\\Users\\Novy\\Desktop\\Projects\\Official YVON\\app\\api\\health\\route.ts", "source_location": "L30"}, {"caller_nid": "route_get", "callee": "join", "source_file": "C:\\Users\\Novy\\Desktop\\Projects\\Official YVON\\app\\api\\health\\route.ts", "source_location": "L33"}, {"caller_nid": "route_get", "callee": "json", "source_file": "C:\\Users\\Novy\\Desktop\\Projects\\Official YVON\\app\\api\\health\\route.ts", "source_location": "L39"}]}