{"nodes": [{"id": "c_users_novy_desktop_projects_official_yvon_app_screens_settings_war_room_page_tsx", "label": "page.tsx", "file_type": "code", "source_file": "C:\\Users\\Novy\\Desktop\\Projects\\Official YVON\\app\\screens\\settings\\war-room\\page.tsx", "source_location": "L1"}, {"id": "page_load", "label": "load()", "file_type": "code", "source_file": "C:\\Users\\Novy\\Desktop\\Projects\\Official YVON\\app\\screens\\settings\\war-room\\page.tsx", "source_location": "L135"}, {"id": "page_save", "label": "save()", "file_type": "code", "source_file": "C:\\Users\\Novy\\Desktop\\Projects\\Official YVON\\app\\screens\\settings\\war-room\\page.tsx", "source_location": "L148"}, {"id": "page_remove", "label": "remove()", "file_type": "code", "source_file": "C:\\Users\\Novy\\Desktop\\Projects\\Official YVON\\app\\screens\\settings\\war-room\\page.tsx", "source_location": "L164"}], "edges": [{"source": "c_users_novy_desktop_projects_official_yvon_app_screens_settings_war_room_page_tsx", "target": "react", "relation": "imports_from", "confidence": "EXTRACTED", "source_file": "C:\\Users\\Novy\\Desktop\\Projects\\Official YVON\\app\\screens\\settings\\war-room\\page.tsx", "source_location": "L3", "weight": 1.0}, {"source": "c_users_novy_desktop_projects_official_yvon_app_screens_settings_war_room_page_tsx", "target": "c_users_novy_desktop_projects_official_yvon_app_screens_settings_shared", "relation": "imports_from", "confidence": "EXTRACTED", "source_file": "C:\\Users\\Novy\\Desktop\\Projects\\Official YVON\\app\\screens\\settings\\war-room\\page.tsx", "source_location": "L4", "weight": 1.0}, {"source": "c_users_novy_desktop_projects_official_yvon_app_screens_settings_war_room_page_tsx", "target": "page_load", "relation": "contains", "confidence": "EXTRACTED", "source_file": "C:\\Users\\Novy\\Desktop\\Projects\\Official YVON\\app\\screens\\settings\\war-room\\page.tsx", "source_location": "L135", "weight": 1.0}, {"source": "c_users_novy_desktop_projects_official_yvon_app_screens_settings_war_room_page_tsx", "target": "page_save", "relation": "contains", "confidence": "EXTRACTED", "source_file": "C:\\Users\\Novy\\Desktop\\Projects\\Official YVON\\app\\screens\\settings\\war-room\\page.tsx", "source_location": "L148", "weight": 1.0}, {"source": "c_users_novy_desktop_projects_official_yvon_app_screens_settings_war_room_page_tsx", "target": "page_remove", "relation": "contains", "confidence": "EXTRACTED", "source_file": "C:\\Users\\Novy\\Desktop\\Projects\\Official YVON\\app\\screens\\settings\\war-room\\page.tsx", "source_location": "L164", "weight": 1.0}, {"source": "page_save", "target": "page_load", "relation": "calls", "confidence": "EXTRACTED", "source_file": "C:\\Users\\Novy\\Desktop\\Projects\\Official YVON\\app\\screens\\settings\\war-room\\page.tsx", "source_location": "L159", "weight": 1.0}, {"source": "page_remove", "target": "page_load", "relation": "calls", "confidence": "EXTRACTED", "source_file": "C:\\Users\\Novy\\Desktop\\Projects\\Official YVON\\app\\screens\\settings\\war-room\\page.tsx", "source_location": "L171", "weight": 1.0}], "raw_calls": [{"caller_nid": "page_load", "callee": "setLoading", "source_file": "C:\\Users\\Novy\\Desktop\\Projects\\Official YVON\\app\\screens\\settings\\war-room\\page.tsx", "source_location": "L136"}, {"caller_nid": "page_load", "callee": "setError", "source_file": "C:\\Users\\Novy\\Desktop\\Projects\\Official YVON\\app\\screens\\settings\\war-room\\page.tsx", "source_location": "L136"}, {"caller_nid": "page_load", "callee": "fetch", "source_file": "C:\\Users\\Novy\\Desktop\\Projects\\Official YVON\\app\\screens\\settings\\war-room\\page.tsx", "source_location": "L138"}, {"caller_nid": "page_load", "callee": "json", "source_file": "C:\\Users\\Novy\\Desktop\\Projects\\Official YVON\\app\\screens\\settings\\war-room\\page.tsx", "source_location": "L139"}, {"caller_nid": "page_load", "callee": "setCustom", "source_file": "C:\\Users\\Novy\\Desktop\\Projects\\Official YVON\\app\\screens\\settings\\war-room\\page.tsx", "source_location": "L141"}, {"caller_nid": "page_load", "callee": "setError", "source_file": "C:\\Users\\Novy\\Desktop\\Projects\\Official YVON\\app\\screens\\settings\\war-room\\page.tsx", "source_location": "L142"}, {"caller_nid": "page_load", "callee": "String", "source_file": "C:\\Users\\Novy\\Desktop\\Projects\\Official YVON\\app\\screens\\settings\\war-room\\page.tsx", "source_location": "L142"}, {"caller_nid": "page_load", "callee": "setLoading", "source_file": "C:\\Users\\Novy\\Desktop\\Projects\\Official YVON\\app\\screens\\settings\\war-room\\page.tsx", "source_location": "L143"}, {"caller_nid": "page_save", "callee": "setSaving", "source_file": "C:\\Users\\Novy\\Desktop\\Projects\\Official YVON\\app\\screens\\settings\\war-room\\page.tsx", "source_location": "L149"}, {"caller_nid": "page_save", "callee": "setError", "source_file": "C:\\Users\\Novy\\Desktop\\Projects\\Official YVON\\app\\screens\\settings\\war-room\\page.tsx", "source_location": "L149"}, {"caller_nid": "page_save", "callee": "fetch", "source_file": "C:\\Users\\Novy\\Desktop\\Projects\\Official YVON\\app\\screens\\settings\\war-room\\page.tsx", "source_location": "L151"}, {"caller_nid": "page_save", "callee": "stringify", "source_file": "C:\\Users\\Novy\\Desktop\\Projects\\Official YVON\\app\\screens\\settings\\war-room\\page.tsx", "source_location": "L154"}, {"caller_nid": "page_save", "callee": "json", "source_file": "C:\\Users\\Novy\\Desktop\\Projects\\Official YVON\\app\\screens\\settings\\war-room\\page.tsx", "source_location": "L156"}, {"caller_nid": "page_save", "callee": "setAddOpen", "source_file": "C:\\Users\\Novy\\Desktop\\Projects\\Official YVON\\app\\screens\\settings\\war-room\\page.tsx", "source_location": "L158"}, {"caller_nid": "page_save", "callee": "setEditCmd", "source_file": "C:\\Users\\Novy\\Desktop\\Projects\\Official YVON\\app\\screens\\settings\\war-room\\page.tsx", "source_location": "L158"}, {"caller_nid": "page_save", "callee": "setError", "source_file": "C:\\Users\\Novy\\Desktop\\Projects\\Official YVON\\app\\screens\\settings\\war-room\\page.tsx", "source_location": "L160"}, {"caller_nid": "page_save", "callee": "String", "source_file": "C:\\Users\\Novy\\Desktop\\Projects\\Official YVON\\app\\screens\\settings\\war-room\\page.tsx", "source_location": "L160"}, {"caller_nid": "page_save", "callee": "setSaving", "source_file": "C:\\Users\\Novy\\Desktop\\Projects\\Official YVON\\app\\screens\\settings\\war-room\\page.tsx", "source_location": "L161"}, {"caller_nid": "page_remove", "callee": "confirm", "source_file": "C:\\Users\\Novy\\Desktop\\Projects\\Official YVON\\app\\screens\\settings\\war-room\\page.tsx", "source_location": "L165"}, {"caller_nid": "page_remove", "callee": "setDeleting", "source_file": "C:\\Users\\Novy\\Desktop\\Projects\\Official YVON\\app\\screens\\settings\\war-room\\page.tsx", "source_location": "L166"}, {"caller_nid": "page_remove", "callee": "setError", "source_file": "C:\\Users\\Novy\\Desktop\\Projects\\Official YVON\\app\\screens\\settings\\war-room\\page.tsx", "source_location": "L166"}, {"caller_nid": "page_remove", "callee": "fetch", "source_file": "C:\\Users\\Novy\\Desktop\\Projects\\Official YVON\\app\\screens\\settings\\war-room\\page.tsx", "source_location": "L168"}, {"caller_nid": "page_remove", "callee": "encodeURIComponent", "source_file": "C:\\Users\\Novy\\Desktop\\Projects\\Official YVON\\app\\screens\\settings\\war-room\\page.tsx", "source_location": "L168"}, {"caller_nid": "page_remove", "callee": "json", "source_file": "C:\\Users\\Novy\\Desktop\\Projects\\Official YVON\\app\\screens\\settings\\war-room\\page.tsx", "source_location": "L169"}, {"caller_nid": "page_remove", "callee": "setError", "source_file": "C:\\Users\\Novy\\Desktop\\Projects\\Official YVON\\app\\screens\\settings\\war-room\\page.tsx", "source_location": "L172"}, {"caller_nid": "page_remove", "callee": "String", "source_file": "C:\\Users\\Novy\\Desktop\\Projects\\Official YVON\\app\\screens\\settings\\war-room\\page.tsx", "source_location": "L172"}, {"caller_nid": "page_remove", "callee": "setDeleting", "source_file": "C:\\Users\\Novy\\Desktop\\Projects\\Official YVON\\app\\screens\\settings\\war-room\\page.tsx", "source_location": "L173"}]}